README.md
setup.py
scripts/om_expand
scripts/om_expand.cmd
vecnet/__init__.py
vecnet.openmalaria.egg-info/PKG-INFO
vecnet.openmalaria.egg-info/SOURCES.txt
vecnet.openmalaria.egg-info/dependency_links.txt
vecnet.openmalaria.egg-info/namespace_packages.txt
vecnet.openmalaria.egg-info/requires.txt
vecnet.openmalaria.egg-info/top_level.txt
vecnet/openmalaria/__about__.py
vecnet/openmalaria/__init__.py
vecnet/openmalaria/cts.py
vecnet/openmalaria/experiment.py
vecnet/openmalaria/healthsystem.py
vecnet/openmalaria/helpers.py
vecnet/openmalaria/monitoring.py
vecnet/openmalaria/output_parser.py
vecnet/openmalaria/bin/__init__.py
vecnet/openmalaria/bin/expand.py
vecnet/openmalaria/scenario/__init__.py
vecnet/openmalaria/scenario/core.py
vecnet/openmalaria/scenario/demography.py
vecnet/openmalaria/scenario/entomology.py
vecnet/openmalaria/scenario/healthsystem.py
vecnet/openmalaria/scenario/interventions.py
vecnet/openmalaria/scenario/monitoring.py
vecnet/openmalaria/scenario/scenario.py
vecnet/openmalaria/tests/__init__.py
vecnet/openmalaria/tests/test_deployment.py
vecnet/openmalaria/tests/test_experiment.py
vecnet/openmalaria/tests/test_get_schema_version.py
vecnet/openmalaria/tests/test_healthsystem.py
vecnet/openmalaria/tests/test_output_parser.py
vecnet/openmalaria/tests/scenario/__init__.py
vecnet/openmalaria/tests/scenario/test_scenario.py
vecnet/openmalaria/tests/scenario/monitoring/__init__.py
vecnet/openmalaria/tests/scenario/monitoring/test_set_survey_times.py