Metadata-Version: 1.1
Name: vecnet.openmalaria
Version: 0.9.6
Summary: Openmalaria library for VecNet-CI project
Home-page: https://github.com/vecnet/vecnet.openmalaria
Author: University of Notre Dame
Author-email: vecnet@nd.edu
License: MPL 2.0
Keywords: openmalaria malaria vecnet
Platform: UNKNOWN
Classifier: Development Status :: 5 - Production/Stable
Classifier: License :: OSI Approved :: Mozilla Public License 2.0 (MPL 2.0)
Classifier: Intended Audience :: Developers
Classifier: Operating System :: OS Independent
Classifier: Programming Language :: Python
Classifier: Programming Language :: Python :: 2
Classifier: Programming Language :: Python :: 3
Classifier: Programming Language :: Python :: 2.7
Classifier: Programming Language :: Python :: 3.5
Classifier: Topic :: Software Development :: Libraries :: Python Modules
